odoo/addons/sale_coupon_product_management/README.rst
odoo/addons/sale_coupon_product_management/__init__.py
odoo/addons/sale_coupon_product_management/__manifest__.py
odoo/addons/sale_coupon_product_management/i18n/fr.po
odoo/addons/sale_coupon_product_management/i18n/sale_coupon_product_management.pot
odoo/addons/sale_coupon_product_management/models/__init__.py
odoo/addons/sale_coupon_product_management/models/product_category.py
odoo/addons/sale_coupon_product_management/models/product_product.py
odoo/addons/sale_coupon_product_management/models/sale_coupon_program.py
odoo/addons/sale_coupon_product_management/readme/CONTRIBUTORS.rst
odoo/addons/sale_coupon_product_management/readme/DESCRIPTION.rst
odoo/addons/sale_coupon_product_management/static/description/icon.png
odoo/addons/sale_coupon_product_management/static/description/index.html
odoo/addons/sale_coupon_product_management/tests/__init__.py
odoo/addons/sale_coupon_product_management/tests/common.py
odoo/addons/sale_coupon_product_management/tests/test_sale_coupon_manage.py
odoo/addons/sale_coupon_product_management/views/product_category_views.xml
odoo/addons/sale_coupon_product_management/views/product_product_views.xml
odoo/addons/sale_coupon_product_management/views/sale_coupon_program_views.xml
odoo13_addon_sale_coupon_product_management-13.0.1.0.1.dist-info/METADATA
odoo13_addon_sale_coupon_product_management-13.0.1.0.1.dist-info/WHEEL
odoo13_addon_sale_coupon_product_management-13.0.1.0.1.dist-info/top_level.txt
odoo13_addon_sale_coupon_product_management-13.0.1.0.1.dist-info/RECORD
